pydeployhelp/__init__.py
pydeployhelp/base.py
pydeployhelp/deploy.py
pydeployhelp/quickstart.py
pydeployhelp/utils.py
pydeployhelp-1.5.0.dist-info/LICENSE
pydeployhelp-1.5.0.dist-info/METADATA
pydeployhelp-1.5.0.dist-info/WHEEL
pydeployhelp-1.5.0.dist-info/entry_points.txt
pydeployhelp-1.5.0.dist-info/top_level.txt
pydeployhelp-1.5.0.dist-info/RECORD
